Metadata-Version: 2.1
Name: mapfw
Version: 0.8.0
Summary: API client for mapfw challenges
Home-page: https://github.com/noahiscool13/mapfw-client
Author: Noah Jadoenathmisier
Author-email: n.j.m.jadoenathmisier@student.tudelft.nl
License: MIT
Platform: UNKNOWN
